{
    "default": {
        "spriteMultiplicity": 1,
        "isRangedWeapon": false,
        "effectData": {}
    },
    "bomb": {
        "spritePos": [0, 2],
        "effect": "spawnFusedBomb"
    },
    "handgun": {
        "spritePos": [1, 2],
        "isRangedWeapon": true,
        "effect": "shootProjectile",
        "range": 12,
        "damage": 20,
        "lineOfFireWidth": 0.5
    },
    "health pack": {
        "spritePos": [3, 2],
        "effect": "healSelf",
        "healAmount": 50
    },
    "green potion": {
        "spritePos": [0, 4],
        "effect": "spawnGreenSlimeBomb",
    },
    "invisibility potion": {
        "spritePos": [3, 5],
        "effect": "invisibility",
        "duration": 10
    },
    "levitation potion": {
        "spritePos": [1, 5],
        "effect": "levitation",
        "duration": 10
    },
    "speed potion": {
        "spritePos": [0, 5],
        "effect": "boostSpeed",
        "duration": 10,
        "boostMultiplier": 2
    }
}
